{"title":"北京推来京人员自主申报及网上申领居住登记卡便民措施-中新网","content":" \n　　中新网4月30日电 据北京市居住证微信公众号消息，2020年4月30日起，北京市居住证微信公众号正式开通“来京人员自主申报”业务功能，根据相关法规，以及市委市政府在新型冠状病毒感染肺炎疫情社区防控工作中的相关规定，来京人员可立即登记本人身份信息，如实填报在京居住信息，依法按需办理居住证卡业务，平台会确保个人信息安全。\n\n　　所有来京流动人口(包括已办理居住证或居住登记卡人员)要通过自主申报→来京人员申报个人信息(上传本人身份证件，录入最新的居住地址，完成疫情问卷)，有需要的群众可以在完成申报环节以后在线申领居住登记卡。\n\n(戳图查看流程)\n\n▽▽▽　　\n\n　　01 申报登记环节\n\n　　\n\n　　02 线上申请居住登记卡环节  \n\n　　\n\n　　\n\n\n\n\n\n\n\n\n\n\n 【编辑:吉翔】 \n      ","publish_date":"2020-04-30","url":"http://www.chinanews.com//gn/2020/04-30/9172438.shtml","source_name":"中国新闻网","source_encoding":"utf-8","crawltime":"2020-05-04T23:09:06.446Z","keywords":"居住证,微信,公众号,登记卡,业务功能","author":"责任编辑：吉翔","source":"来源：中国新闻网","desc":"所有来京流动人口(包括已办理居住证或居住登记卡人员)要通过自主申报→来京人员申报个人信息(上传本人身份证件，录入最新的居住地址，完成疫情问卷)，有需要的群众可以在完成申报环节以后在线申领居住登记卡。(戳图查看流程)▽▽▽　　　　01 申报登记环节　　　　02 线上申请居住登记卡环节。"}